{
    "nodes": [
        {
            "id": 0,
            "name": "account_00000000000000081479",
            "val": 5.022796900645753,
            "color": "#ccffcc"
        },
        {
            "id": 1,
            "name": "advisor_4162",
            "val": 40,
            "color": "blue"
        },
        {
            "id": 2,
            "name": "client_189190",
            "val": 10,
            "color": "#b3ccff"
        },
        {
            "id": 3,
            "name": "account_00000000000000109121",
            "val": 5.803688076825446,
            "color": "#ccffcc"
        },
        {
            "id": 4,
            "name": "client_188154",
            "val": 10,
            "color": "#b3ccff"
        },
        {
            "id": 5,
            "name": "account_00000000000000109703",
            "val": 5.466164736357393,
            "color": "#9999ff"
        },
        {
            "id": 6,
            "name": "client_188126",
            "val": 10,
            "color": "#b3ccff"
        },
        {
            "id": 7,
            "name": "account_00000000000000112533",
            "val": 4.883085968685246,
            "color": "#ccffcc"
        },
        {
            "id": 8,
            "name": "client_188139",
            "val": 10,
            "color": "#b3ccff"
        },
        {
            "id": 9,
            "name": "account_00000000000000112534",
            "val": 5.260567665180669,
            "color": "#ccffcc"
        },
        {
            "id": 10,
            "name": "account_00000000000000112535",
            "val": 5.659324878486032,
            "color": "#ccffcc"
        },
        {
            "id": 11,
            "name": "client_188093",
            "val": 10,
            "color": "#b3ccff"
        },
        {
            "id": 12,
            "name": "account_00000000000000112536",
            "val": 5.564700331823331,
            "color": "#ccffcc"
        },
        {
            "id": 13,
            "name": "account_00000000000000112537",
            "val": 4.41641834483869,
            "color": "#ccffcc"
        },
        {
            "id": 14,
            "name": "client_188167",
            "val": 10,
            "color": "#b3ccff"
        },
        {
            "id": 15,
            "name": "account_00000000000000112602",
            "val": 5.014506983980408,
            "color": "#ccffcc"
        },
        {
            "id": 16,
            "name": "client_188107",
            "val": 10,
            "color": "#b3ccff"
        },
        {
            "id": 17,
            "name": "account_00000000000000112603",
            "val": 5.6259722726236125,
            "color": "#ccffcc"
        },
        {
            "id": 18,
            "name": "client_188137",
            "val": 10,
            "color": "#b3ccff"
        },
        {
            "id": 19,
            "name": "account_00000000000000112604",
            "val": 6.071960793931055,
            "color": "#ccffcc"
        },
        {
            "id": 20,
            "name": "account_00000000000000112605",
            "val": 5.495284126648821,
            "color": "#ccffcc"
        },
        {
            "id": 21,
            "name": "account_00000000000000112606",
            "val": 5.399180059800077,
            "color": "#9999ff"
        },
        {
            "id": 22,
            "name": "client_188159",
            "val": 10,
            "color": "#b3ccff"
        },
        {
            "id": 23,
            "name": "account_00000000000000112653",
            "val": 5.395478920371501,
            "color": "#ccffcc"
        },
        {
            "id": 24,
            "name": "client_188162",
            "val": 10,
            "color": "#b3ccff"
        },
        {
            "id": 25,
            "name": "account_00000000000000112654",
            "val": 5.308150430774833,
            "color": "#ccffcc"
        },
        {
            "id": 26,
            "name": "client_188141",
            "val": 10,
            "color": "#b3ccff"
        },
        {
            "id": 27,
            "name": "account_00000000000000112695",
            "val": 4.089999393245385,
            "color": "#9999ff"
        },
        {
            "id": 28,
            "name": "client_188177",
            "val": 10,
            "color": "#b3ccff"
        },
        {
            "id": 29,
            "name": "account_00000000000000112696",
            "val": 5.804460574684397,
            "color": "#9999ff"
        },
        {
            "id": 30,
            "name": "client_189143",
            "val": 10,
            "color": "#b3ccff"
        },
        {
            "id": 31,
            "name": "account_00000000000000112697",
            "val": 4.553570173434223,
            "color": "#ccffcc"
        },
        {
            "id": 32,
            "name": "client_188178",
            "val": 10,
            "color": "#b3ccff"
        },
        {
            "id": 33,
            "name": "account_00000000000000112698",
            "val": 5.642600152317193,
            "color": "#9999ff"
        },
        {
            "id": 34,
            "name": "client_188088",
            "val": 10,
            "color": "#b3ccff"
        },
        {
            "id": 35,
            "name": "account_00000000000000112699",
            "val": 5.677253870377145,
            "color": "#ccffcc"
        },
        {
            "id": 36,
            "name": "client_188135",
            "val": 10,
            "color": "#b3ccff"
        },
        {
            "id": 37,
            "name": "account_00000000000000112700",
            "val": 5.141411582623993,
            "color": "#ccffcc"
        },
        {
            "id": 38,
            "name": "client_188091",
            "val": 10,
            "color": "#b3ccff"
        },
        {
            "id": 39,
            "name": "account_00000000000000112701",
            "val": 4.279836738014372,
            "color": "#ccffcc"
        },
        {
            "id": 40,
            "name": "account_00000000000000112702",
            "val": 5.5244477713435804,
            "color": "#ccffcc"
        },
        {
            "id": 41,
            "name": "client_188170",
            "val": 10,
            "color": "#b3ccff"
        },
        {
            "id": 42,
            "name": "account_00000000000000112703",
            "val": 4.421203298610613,
            "color": "#ccffcc"
        },
        {
            "id": 43,
            "name": "client_188106",
            "val": 10,
            "color": "#b3ccff"
        }
    ],
    "links": [
        {
            "source": 1,
            "target": 2
        },
        {
            "source": 2,
            "target": 0
        },
        {
            "source": 1,
            "target": 4
        },
        {
            "source": 4,
            "target": 3
        },
        {
            "source": 1,
            "target": 6
        },
        {
            "source": 6,
            "target": 5
        },
        {
            "source": 1,
            "target": 8
        },
        {
            "source": 8,
            "target": 7
        },
        {
            "source": 8,
            "target": 9
        },
        {
            "source": 1,
            "target": 11
        },
        {
            "source": 11,
            "target": 10
        },
        {
            "source": 8,
            "target": 12
        },
        {
            "source": 1,
            "target": 14
        },
        {
            "source": 14,
            "target": 13
        },
        {
            "source": 1,
            "target": 16
        },
        {
            "source": 16,
            "target": 15
        },
        {
            "source": 1,
            "target": 18
        },
        {
            "source": 18,
            "target": 17
        },
        {
            "source": 18,
            "target": 19
        },
        {
            "source": 4,
            "target": 20
        },
        {
            "source": 1,
            "target": 22
        },
        {
            "source": 22,
            "target": 21
        },
        {
            "source": 1,
            "target": 24
        },
        {
            "source": 24,
            "target": 23
        },
        {
            "source": 1,
            "target": 26
        },
        {
            "source": 26,
            "target": 25
        },
        {
            "source": 1,
            "target": 28
        },
        {
            "source": 28,
            "target": 27
        },
        {
            "source": 1,
            "target": 30
        },
        {
            "source": 30,
            "target": 29
        },
        {
            "source": 1,
            "target": 32
        },
        {
            "source": 32,
            "target": 31
        },
        {
            "source": 1,
            "target": 34
        },
        {
            "source": 34,
            "target": 33
        },
        {
            "source": 1,
            "target": 36
        },
        {
            "source": 36,
            "target": 35
        },
        {
            "source": 1,
            "target": 38
        },
        {
            "source": 38,
            "target": 37
        },
        {
            "source": 32,
            "target": 39
        },
        {
            "source": 1,
            "target": 41
        },
        {
            "source": 41,
            "target": 40
        },
        {
            "source": 1,
            "target": 43
        },
        {
            "source": 43,
            "target": 42
        }
    ]
}